commitmessage/__init__.py
commitmessage/drama.py
commitmessage/emoji.py
commitmessage/haiku.py
commitmessage/style.py
commitmessage-0.2.0.dist-info/LICENSE
commitmessage-0.2.0.dist-info/METADATA
commitmessage-0.2.0.dist-info/WHEEL
commitmessage-0.2.0.dist-info/top_level.txt
commitmessage-0.2.0.dist-info/RECORD
