Metadata-Version: 2.2
Name: commitmessage
Version: 0.2.0
Summary: Generate creative, funny, or themed git commit messages
Author: Brian Zou, Cyryl Zhang, Josh Lavroff
Author-email: Johnny Ding <yd2960@example.com>
License: MIT
License-File: LICENSE
